{"version":3,"kind":"Notebook","sha256":"fe7867896d134292e46ffda35e39a1a274dd64c360084fbdc36b8369c8cbe840","slug":"iterations-and-comprehensions","location":"/02 Essentials/04_iterations_and_comprehensions.ipynb","dependencies":[],"frontmatter":{"title":"Iterations and Comprehensions","content_includes_title":false,"kernelspec":{"name":"python3","display_name":"Python 3 (ipykernel)","language":"python"},"numbering":{"title":{"offset":1}},"thumbnail":"/learnpython/build/dl-nb.png-894f385aa69c711e8729978a307d6667.png","exports":[{"format":"ipynb","filename":"04_iterations_and_comprehensions.ipynb","url":"/learnpython/build/04_iterations_and_co-6bd1003adf77cee3130b50a45bf04d90.ipynb"}]},"widgets":{},"mdast":{"type":"root","children":[{"type":"block","kind":"notebook-content","data":{"editable":true,"slideshow":{"slide_type":""},"tags":[]},"children":[{"type":"admonition","kind":"tip","children":[{"type":"admonitionTitle","children":[{"type":"text","value":"DOWNLOAD THE NOTEBOOK TO RUN LOCALLY","position":{"start":{"line":2,"column":1},"end":{"line":2,"column":1}},"key":"BJYJw2pexR"}],"key":"H9g5ZeMydA"},{"type":"paragraph","position":{"start":{"line":4,"column":1},"end":{"line":4,"column":1}},"children":[{"type":"text","value":"Click the download button (","position":{"start":{"line":4,"column":1},"end":{"line":4,"column":1}},"key":"qxzqMmY3b0"},{"type":"image","url":"/learnpython/build/dl-nb.png-894f385aa69c711e8729978a307d6667.png","position":{"start":{"line":4,"column":1},"end":{"line":4,"column":1}},"urlSource":"../assets/img/site/dl-nb.png.png","key":"bBuS58yWeA"},{"type":"text","value":") on the upper right to download the notebook and run them locally.","position":{"start":{"line":4,"column":1},"end":{"line":4,"column":1}},"key":"KZmxhRZ9pL"}],"key":"LXfV5eBS2Y"}],"key":"eajvv2I3M3"}],"visibility":"show","key":"uvuOXMWwU4"},{"type":"block","kind":"notebook-content","data":{"editable":true,"slideshow":{"slide_type":""},"tags":[]},"children":[{"type":"heading","depth":2,"position":{"start":{"line":1,"column":1},"end":{"line":1,"column":1}},"children":[{"type":"text","value":"Iterations","position":{"start":{"line":1,"column":1},"end":{"line":1,"column":1}},"key":"cOatBWZgB8"}],"identifier":"iterations","label":"Iterations","html_id":"iterations","implicit":true,"key":"ubcWjKYrRf"},{"type":"paragraph","position":{"start":{"line":2,"column":1},"end":{"line":2,"column":1}},"children":[{"type":"text","value":"Beyond standard ","position":{"start":{"line":2,"column":1},"end":{"line":2,"column":1}},"key":"f7dnNfQcno"},{"type":"inlineCode","value":"for","position":{"start":{"line":2,"column":1},"end":{"line":2,"column":1}},"key":"zLEjbZr5dd"},{"type":"text","value":" loops, Python provides powerful tools to iterate through data efficiently.","position":{"start":{"line":2,"column":1},"end":{"line":2,"column":1}},"key":"BR9QsqtRCt"}],"key":"wo61jb2ukA"},{"type":"heading","depth":3,"position":{"start":{"line":4,"column":1},"end":{"line":4,"column":1}},"children":[{"type":"inlineCode","value":"enumerate()","position":{"start":{"line":4,"column":1},"end":{"line":4,"column":1}},"key":"P32fo8j74O"}],"identifier":"enumerate","label":"enumerate()","html_id":"enumerate","implicit":true,"key":"gEczhnpwpl"},{"type":"paragraph","position":{"start":{"line":5,"column":1},"end":{"line":5,"column":1}},"children":[{"type":"text","value":"Use this when you need both the ","position":{"start":{"line":5,"column":1},"end":{"line":5,"column":1}},"key":"ECT6TXQOtR"},{"type":"strong","position":{"start":{"line":5,"column":1},"end":{"line":5,"column":1}},"children":[{"type":"text","value":"index","position":{"start":{"line":5,"column":1},"end":{"line":5,"column":1}},"key":"xO5MUaa9nM"}],"key":"l7aNEwjpV0"},{"type":"text","value":" (counter) and the ","position":{"start":{"line":5,"column":1},"end":{"line":5,"column":1}},"key":"H9FFaTo6t6"},{"type":"strong","position":{"start":{"line":5,"column":1},"end":{"line":5,"column":1}},"children":[{"type":"text","value":"value","position":{"start":{"line":5,"column":1},"end":{"line":5,"column":1}},"key":"T2PF184fLK"}],"key":"nIUHMbESCY"},{"type":"text","value":" inside a loop.","position":{"start":{"line":5,"column":1},"end":{"line":5,"column":1}},"key":"aETXqGfHP5"}],"key":"gsFqEsZpeX"}],"visibility":"show","key":"ODH1MgDsnf"},{"type":"block","kind":"notebook-code","data":{"editable":true,"slideshow":{"slide_type":""},"tags":[]},"children":[{"type":"code","lang":"python","executable":true,"value":"# number the regions for a report\nregions = [\"NCR\", \"CAR\", \"Region I\", \"Region II\"]\n\n# `i` is the index, `region` is the value\nfor i, region in enumerate(regions, start=1):\n    print(f\"Region Code {i}: {region}\")","visibility":"show","key":"fKrAwShjEY"},{"type":"outputs","id":"dr3ghHHSJXbhSiD4YEHh1","children":[{"type":"output","jupyter_data":{"name":"stdout","output_type":"stream","text":"Region Code 1: NCR\nRegion Code 2: CAR\nRegion Code 3: Region I\nRegion Code 4: Region II\n"},"children":[],"key":"izH1JuEV2A"}],"visibility":"hide","key":"Il1eWiDF9A"}],"visibility":"show","key":"dzXqmyapxT"},{"type":"block","kind":"notebook-content","data":{"editable":true,"slideshow":{"slide_type":""},"tags":[]},"children":[{"type":"heading","depth":3,"position":{"start":{"line":1,"column":1},"end":{"line":1,"column":1}},"children":[{"type":"inlineCode","value":"zip()","position":{"start":{"line":1,"column":1},"end":{"line":1,"column":1}},"key":"XSZobSidxm"}],"identifier":"zip","label":"zip()","html_id":"zip","implicit":true,"key":"citDEyUhSH"},{"type":"paragraph","position":{"start":{"line":3,"column":1},"end":{"line":4,"column":1}},"children":[{"type":"text","value":"Used to iterate over ","position":{"start":{"line":3,"column":1},"end":{"line":3,"column":1}},"key":"u1n8XrGZvp"},{"type":"strong","position":{"start":{"line":3,"column":1},"end":{"line":3,"column":1}},"children":[{"type":"text","value":"two lists at the same time","position":{"start":{"line":3,"column":1},"end":{"line":3,"column":1}},"key":"MNFLq8yIrH"}],"key":"ZphgdyXqyx"},{"type":"text","value":".\nThis is common when you have separate columns of data (e.g., a list of provinces and a list of populations).","position":{"start":{"line":3,"column":1},"end":{"line":3,"column":1}},"key":"xlVnu7xPFF"}],"key":"jmRgwdrboX"}],"visibility":"show","key":"lMAlcQJPNY"},{"type":"block","kind":"notebook-code","data":{"editable":true,"slideshow":{"slide_type":""},"tags":[]},"children":[{"type":"code","lang":"python","executable":true,"value":"provinces = [\"Cavite\", \"Laguna\", \"Batangas\"]\npopulations = [4.3, 3.4, 2.9] # in millions\n\n# Loop through both lists simultaneously\nfor prov, pop in zip(provinces, populations):\n    print(f\"{prov} has a population of {pop} million\")","visibility":"show","key":"p2KDGluuaL"},{"type":"outputs","id":"HefexvJhpytuz_rJj8l0v","children":[{"type":"output","jupyter_data":{"name":"stdout","output_type":"stream","text":"Cavite has a population of 4.3 million\nLaguna has a population of 3.4 million\nBatangas has a population of 2.9 million\n"},"children":[],"key":"f5trMCzbpB"}],"visibility":"hide","key":"uMqS7NBsBu"}],"visibility":"show","key":"qdewJjHU2S"},{"type":"block","kind":"notebook-content","children":[{"type":"heading","depth":2,"position":{"start":{"line":1,"column":1},"end":{"line":1,"column":1}},"children":[{"type":"text","value":"List Comprehensions","position":{"start":{"line":1,"column":1},"end":{"line":1,"column":1}},"key":"i6ZBkNYjdd"}],"identifier":"list-comprehensions","label":"List Comprehensions","html_id":"list-comprehensions","implicit":true,"key":"Ya8Er1TdFU"},{"type":"paragraph","position":{"start":{"line":3,"column":1},"end":{"line":3,"column":1}},"children":[{"type":"text","value":"A concise way to create lists.","position":{"start":{"line":3,"column":1},"end":{"line":3,"column":1}},"key":"vfcjkGF81l"}],"key":"C7Rsz2hr6V"}],"key":"EJFd63yYK4"},{"type":"block","kind":"notebook-code","data":{"editable":true,"slideshow":{"slide_type":""},"tags":[]},"children":[{"type":"code","lang":"python","executable":true,"value":"raw_data = [10, 20, 30, 40, 50]\n\ndoubled_data= [x * 2 for x in raw_data]\nprint(doubled_data)\n\n# replaces these lines:\n# doubled_data = []\n\n# for x in raw_data:\n   # doubled_data.append(x * 2)","visibility":"show","key":"EpeOPC9cDo"},{"type":"outputs","id":"EEVqutN4VeV8RW3R_emw3","children":[{"type":"output","jupyter_data":{"name":"stdout","output_type":"stream","text":"[20, 40, 60, 80, 100]\n"},"children":[],"key":"Mw7LGuqBtj"}],"visibility":"hide","key":"okDFMnhbpm"}],"visibility":"show","key":"e2lvPVhIeu"},{"type":"block","kind":"notebook-content","children":[{"type":"heading","depth":3,"position":{"start":{"line":1,"column":1},"end":{"line":1,"column":1}},"children":[{"type":"text","value":"Comprehension with Filtering","position":{"start":{"line":1,"column":1},"end":{"line":1,"column":1}},"key":"iTqLqEBy8J"}],"identifier":"comprehension-with-filtering","label":"Comprehension with Filtering","html_id":"comprehension-with-filtering","implicit":true,"key":"Jz7TxRF2LJ"},{"type":"paragraph","position":{"start":{"line":3,"column":1},"end":{"line":3,"column":1}},"children":[{"type":"text","value":"Adding an ","position":{"start":{"line":3,"column":1},"end":{"line":3,"column":1}},"key":"G7gpfVuWj9"},{"type":"inlineCode","value":"if","position":{"start":{"line":3,"column":1},"end":{"line":3,"column":1}},"key":"yOhhYhCWIN"},{"type":"text","value":" statement to filter data instantly.","position":{"start":{"line":3,"column":1},"end":{"line":3,"column":1}},"key":"V4PHQ1Zqoj"}],"key":"kyTYb3uhNb"}],"key":"JcVwGZwfey"},{"type":"block","kind":"notebook-code","data":{"editable":true,"slideshow":{"slide_type":""},"tags":[]},"children":[{"type":"code","lang":"python","executable":true,"value":"# filter out negative entries\nsurvey_ages = [25, 30, -1, 45, 0, 18, -99]\n\nvalid_ages = [age for age in survey_ages if age > 0]\nprint(f\"Valid Ages: {valid_ages}\")","visibility":"show","key":"ZvdiFDwCv2"},{"type":"outputs","id":"_6jbIShiQm8Zbmb4qlMZT","children":[{"type":"output","jupyter_data":{"name":"stdout","output_type":"stream","text":"Valid Ages: [25, 30, 45, 18]\n"},"children":[],"key":"slH0iSM5o8"}],"visibility":"hide","key":"gMkz2iF7cO"}],"visibility":"show","key":"cPqWAXSLks"},{"type":"block","kind":"notebook-content","children":[{"type":"heading","depth":3,"position":{"start":{"line":1,"column":1},"end":{"line":1,"column":1}},"children":[{"type":"text","value":"Dictionary Comprehensions","position":{"start":{"line":1,"column":1},"end":{"line":1,"column":1}},"key":"kWYQi2UnSu"}],"identifier":"dictionary-comprehensions","label":"Dictionary Comprehensions","html_id":"dictionary-comprehensions","implicit":true,"key":"b8IYm6gtP0"},{"type":"paragraph","position":{"start":{"line":2,"column":1},"end":{"line":2,"column":1}},"children":[{"type":"text","value":"Just like lists, you can build dictionaries in one line. This is great for remapping data (e.g., swapping keys and values).","position":{"start":{"line":2,"column":1},"end":{"line":2,"column":1}},"key":"a3Bu6vwtnx"}],"key":"FAwmcWo9Os"}],"key":"zp1CGLBYF6"},{"type":"block","kind":"notebook-code","data":{"editable":true,"slideshow":{"slide_type":""},"tags":[]},"children":[{"type":"code","lang":"python","executable":true,"value":"# create a lookup dictionary for region codes\n\nregions = [\"NCR\", \"CAR\", \"Region I\"]\ncodes = [1300, 1400, 100]\n\n# create a dict: {1300: 'NCR', 1400: 'CAR', ...}\nregion_lookup = {code: name for code, name in zip(codes, regions)}\nprint(region_lookup)\nprint(f\"Code 1400 belongs to: {region_lookup[1400]}\")","visibility":"show","key":"PE1HuvJSmq"},{"type":"outputs","id":"VHQJo2oOuBfn7ttQpqXnn","children":[{"type":"output","jupyter_data":{"name":"stdout","output_type":"stream","text":"{1300: 'NCR', 1400: 'CAR', 100: 'Region I'}\nCode 1400 belongs to: CAR\n"},"children":[],"key":"V9lqxpjbmo"}],"visibility":"hide","key":"t4zhPhp3AN"}],"visibility":"show","key":"HhinDFgrN9"}],"key":"WgiV9OHA9K"},"references":{"cite":{"order":[],"data":{}}},"footer":{"navigation":{"prev":{"title":"Data Structures","url":"/data-structures","group":"Essentials"},"next":{"title":"Functions, Classes, and Objects","url":"/functions-classes-and-objects","group":"Essentials"}}},"domain":"http://localhost:3001"}